README.md
setup.py
./overlapy.py
overlapy.egg-info/PKG-INFO
overlapy.egg-info/SOURCES.txt
overlapy.egg-info/dependency_links.txt
overlapy.egg-info/requires.txt
overlapy.egg-info/top_level.txt