Metadata-Version: 2.1
Name: overlapy
Version: 0.0.1
Summary: Library to help compute textual overlap.
Home-page: https://github.com/nlx-group/overlapy
Author: Ruben Branco, Luís Gomes
Author-email: rmbranco@fc.ul.pt
License: MIT
Keywords: text tool
Platform: UNKNOWN
Classifier: Development Status :: 5 - Production/Stable
Classifier: Intended Audience :: Developers
Classifier: Topic :: Text Processing :: Filters
Classifier: License :: OSI Approved :: MIT License
Classifier: Programming Language :: Python :: 3 :: Only
